cryptbase/__init__.py
cryptbase/cryptbase.py
cryptbase-1.0.0.dist-info/AUTHORS.rst
cryptbase-1.0.0.dist-info/LICENSE
cryptbase-1.0.0.dist-info/METADATA
cryptbase-1.0.0.dist-info/WHEEL
cryptbase-1.0.0.dist-info/top_level.txt
cryptbase-1.0.0.dist-info/RECORD
