Metadata-Version: 2.1
Name: cryptbase
Version: 1.0.0
Summary: Protect yourself and your customers with database encryption.
Home-page: https://code.eghuro.com/cryptbase/python-cryptbase
Author: Alexandr Mansurov
Author-email: alex@eghuro.cz
License: MIT
Project-URL: Documentation, https://python-cryptbase.readthedocs.io/
Project-URL: Changelog, https://python-cryptbase.readthedocs.io/en/latest/changelog.html
Project-URL: Issue Tracker, https://code.eghuro.com/cryptbase/python-cryptbase/issues
Platform: UNKNOWN
Classifier: Development Status :: 5 - Production/Stable
Classifier: Intended Audience :: Developers
Classifier: License :: OSI Approved :: MIT License
Classifier: Operating System :: Unix
Classifier: Operating System :: POSIX
Classifier: Operating System :: Microsoft :: Windows
Classifier: Programming Language :: Python
Classifier: Programming Language :: Python :: 3
Classifier: Programming Language :: Python :: 3 :: Only
Classifier: Programming Language :: Python :: 3.6
Classifier: Programming Language :: Python :: 3.7
Classifier: Programming Language :: Python :: 3.8
Classifier: Programming Language :: Python :: 3.9
Classifier: Programming Language :: Python :: Implementation :: CPython
Classifier: Programming Language :: Python :: Implementation :: PyPy
Classifier: Topic :: Utilities
Requires-Python: >=3.6
License-File: LICENSE
License-File: AUTHORS.rst
Requires-Dist: cryptography
Provides-Extra: django
Requires-Dist: django (>=3.2) ; extra == 'django'
Provides-Extra: sqlalchemy
Requires-Dist: sqlalchemy (>=1.4) ; extra == 'sqlalchemy'
